{"about_index.md":"fd93f392","index.md":"5ed8af18","notes_art_index.md":"eaa38923","notes_art_picture-perfect-posing.md":"8e6dfac5","notes_art_影像叙事语言.md":"d0b66c89","notes_art_摄影构图学.md":"2fa2c499","notes_art_旁轴相机.md":"627d55c4","notes_art_论摄影.md":"f2e76880","notes_art_辐射镜头.md":"b0def14c","notes_index.md":"bc84eeb7","notes_it_index.md":"61f208b2","notes_it_other_app.md":"7e5e80c0","notes_it_other_clashx.md":"3ac261d9","notes_it_other_windows激活.md":"ebf63804","notes_it_other_环境配置.md":"cbbfb10d","notes_it_web_chromeperformance.md":"cc5700ab","notes_it_web_javascript图像处理.md":"818ff4aa","notes_it_web_web存储.md":"9b1971cd","notes_it_web__firefox跨域.md":"afa67dc9","notes_it_web__haida.md":"9778aeaf","notes_it_web__npm源.md":"c2458208","notes_it_web__动态加载.md":"3d061ea2","notes_it_web__打包工具.md":"a98bb7bb","notes_it_web_babel-plugin.md":"cf87792f","notes_it_web_babelrc.md":"115318e7","notes_it_web_charles.md":"851eaceb","notes_it_web_github-actions.md":"8f6863ef","notes_it_web_github-page-error.md":"2874e841","notes_it_web_js中的base64编码转译.md":"bb551948","notes_it_web_object-create.md":"fad71798","notes_it_web_project-version-mark.md":"fc277146","notes_it_web_read-zip-info.md":"dc05bee3","notes_it_web_vitepress-export-pdf.md":"fff9253a","notes_it_web_vitepress-plugin-music.md":"c6adbbc7","notes_it_web_打包javascript库的现代化指南.md":"78195614","notes_it_web_浏览器中的内存泄漏.md":"441a9bab","photographs_2020.md":"732bf9d6","photographs_2021.md":"9d9632c7","photographs_2022.md":"823df33e","photographs_earlier.md":"90ca6425","photographs_index.md":"ca80e700","photographs_li-ya-nan.md":"cccc36fe","photographs_pentaxsp.md":"e162bfe7","posts_index.md":"51cb1df4","posts_me_20221018.md":"43e04bdb","posts_share_movies.md":"d491c29f","project_index.md":"c8f004fb"}
