{"index.md":"57625440","message_index.md":"5d2634f9","notes_art_book_写给无神论者.md":"0336a5bd","notes_art_graph_annieleibovitz.md":"0587c197","notes_art_graph_picture-perfect-posing.md":"7e55d9ee","notes_art_graph_今日摄影.md":"752e2c59","notes_art_graph_他们为何而创作.md":"d9256e2c","notes_art_graph_影像叙事语言.md":"b0c04f32","notes_art_graph_摄影构图学.md":"14174952","notes_art_graph_胶片数码化.md":"09c4067e","notes_art_graph_alecsoth.md":"0d65d3f1","notes_it_web_deploy_github-page-error.md":"8de29c16","notes_art_graph_辐射镜头.md":"edffc8e4","notes_it_other_app.md":"17e91541","notes_it_other_git.md":"01533089","notes_it_other_mac.md":"a6ca267c","notes_it_other_windows激活.md":"5e288cc9","notes_it_other_虚拟定位.md":"82297c1e","notes_art_graph_旁轴相机.md":"6bde68c1","notes_it_other_cmd.md":"2783b836","notes_it_other_环境配置.md":"b03a5aeb","notes_it_web_deploy_github actions部署静态页面.md":"c94fa507","notes_it_other_clashx.md":"4705343b","notes_art_graph_论摄影.md":"4279ad76","notes_it_web_develop_js实现多重继承.md":"7444fb07","notes_it_web_develop_web存储.md":"9d61a062","notes_it_web_develop_babelrc.md":"5b8fd909","notes_it_web_develop_js中的base64编码转译.md":"c5b608af","notes_it_web_develop_webworker.md":"d72f7826","notes_it_web_develop_前端预览zip包信息.md":"a9682988","notes_it_web_develop_协同操作设计.md":"e216862a","notes_it_web_develop_打包javascript库的现代化指南.md":"d119d9f6","notes_it_web_develop_行高与滚动条.md":"5f1ccdc6","notes_it_web_develop_crdt实时协作库工程实现.md":"d4782eb9","notes_it_web_develop_超出显示浮层.md":"d40deaea","notes_it_web_optimization_浏览器中的内存泄漏.md":"041859c5","notes_it_web_develop_前端生称hash值.md":"297c12d3","notes_it_web_graph_javascript图像处理.md":"ba787765","notes_it_web_graph_canvas交互设计.md":"6f7a6b06","notes_it_web_graph_对焦检测原理.md":"6c34db99","notes_it_web_graph_碰撞检测.md":"07d308d7","notes_it_web_graph_解析antv技术栈动画.md":"424ce937","notes_it_web_graph_贝塞尔曲线.md":"156d9d67","notes_it_web_plugin_babel-plugin开发.md":"967f19d4","notes_it_web_plugin_vite-plugin-version-mark.md":"a6c5ff65","notes_it_web_plugin_vitepress-export-pdf.md":"aa94dab7","notes_it_web_plugin_vitepress-plugin-music.md":"6203f306","notes_it_web_plugin_如何命名一个alias.md":"37aed957","notes_it_web_plugin_获得npm包名.md":"ff881b0e","notes_it_web_sourcecode_js精度丢失的处理.md":"b8b88e7b","notes_it_web_sourcecode_vue.md":"94c5497a","notes_it_web__charles.md":"c00cad9c","notes_it_web__haida.md":"065b58f3","notes_it_web__hooks的内存泄露.md":"e42faec6","notes_it_web__npm源.md":"4859ee50","photographs_album_2020.md":"2d4e41bf","photographs_album_2021.md":"bfa483ac","photographs_album_2022.md":"f6c95a02","photographs_album_2023.md":"aabf4432","photographs_album_earlier.md":"3f64c407","photographs_shared_thomasjorion.md":"63b72eb2","photographs_shared_tokyocompression.md":"cdc8edc1","photographs_shared_li-ya-nan.md":"55bd2135","photographs_shared_pentaxsp.md":"8993188b","photographs_shared_zhangkechun.md":"6a5504c3","posts_index.md":"044d7340","posts_me_20221018.md":"a6b23d8b","posts_share_movies.md":"119ab5db","project_index.md":"ef959588","notes_it_web_optimization_chromeperformance.md":"4c6f5511","notes_it_web_optimization_vitebuild优化.md":"528ecc5a","notes_it_web_optimization_创建对象.md":"5766a9be","notes_it_web_optimization_开启gzip.md":"e9bd81f3","notes_it_web_optimization_js中的内存占用.md":"af2f43bf","about_index.md":"98f244a2"}
